x3cflux/__init__.py
x3cflux/experimental_design.py
x3cflux/optimization.py
x3cflux/statistics.py
x3cflux/utilities.py
x3cflux/include/eigen3/signature_of_eigen3_matrix_library
x3cflux/include/eigen3/Eigen/Cholesky
x3cflux/include/eigen3/Eigen/CholmodSupport
x3cflux/include/eigen3/Eigen/Core
x3cflux/include/eigen3/Eigen/Dense
x3cflux/include/eigen3/Eigen/Eigen
x3cflux/include/eigen3/Eigen/Eigenvalues
x3cflux/include/eigen3/Eigen/Geometry
x3cflux/include/eigen3/Eigen/Householder
x3cflux/include/eigen3/Eigen/IterativeLinearSolvers
x3cflux/include/eigen3/Eigen/Jacobi
x3cflux/include/eigen3/Eigen/KLUSupport
x3cflux/include/eigen3/Eigen/LU
x3cflux/include/eigen3/Eigen/MetisSupport
x3cflux/include/eigen3/Eigen/OrderingMethods
x3cflux/include/eigen3/Eigen/PaStiXSupport
x3cflux/include/eigen3/Eigen/PardisoSupport
x3cflux/include/eigen3/Eigen/QR
x3cflux/include/eigen3/Eigen/QtAlignedMalloc
x3cflux/include/eigen3/Eigen/SPQRSupport
x3cflux/include/eigen3/Eigen/SVD
x3cflux/include/eigen3/Eigen/Sparse
x3cflux/include/eigen3/Eigen/SparseCholesky
x3cflux/include/eigen3/Eigen/SparseCore
x3cflux/include/eigen3/Eigen/SparseLU
x3cflux/include/eigen3/Eigen/SparseQR
x3cflux/include/eigen3/Eigen/StdDeque
x3cflux/include/eigen3/Eigen/StdList
x3cflux/include/eigen3/Eigen/StdVector
x3cflux/include/eigen3/Eigen/SuperLUSupport
x3cflux/include/eigen3/Eigen/UmfPackSupport
x3cflux/include/eigen3/Eigen/src/Cholesky/LDLT.h
x3cflux/include/eigen3/Eigen/src/Cholesky/LLT.h
x3cflux/include/eigen3/Eigen/src/Cholesky/LLT_LAPACKE.h
x3cflux/include/eigen3/Eigen/src/CholmodSupport/CholmodSupport.h
x3cflux/include/eigen3/Eigen/src/Core/ArithmeticSequence.h
x3cflux/include/eigen3/Eigen/src/Core/Array.h
x3cflux/include/eigen3/Eigen/src/Core/ArrayBase.h
x3cflux/include/eigen3/Eigen/src/Core/ArrayWrapper.h
x3cflux/include/eigen3/Eigen/src/Core/Assign.h
x3cflux/include/eigen3/Eigen/src/Core/AssignEvaluator.h
x3cflux/include/eigen3/Eigen/src/Core/Assign_MKL.h
x3cflux-3.0.1.dist-info/METADATA
x3cflux-3.0.1.dist-info/WHEEL
x3cflux-3.0.1.dist-info/RECORD
x3cflux-3.0.1.dist-info/licenses/LICENSE
x3cflux-3.0.1.dist-info/sboms/auditwheel.cdx.json
