Metadata-Version: 2.4
Name: x3cflux
Version: 3.0.1
Summary: Python interface for 13CFLUX
Keywords: 13C-MFA,MFA,mass-spectrometry,HPC
Author-Email: Anton Stratmann <info@13cflux.net>, Martin Beyss <info@13cflux.net>, Katharina Noeh <info@13cflux.net>
License-Expression: AGPL-3.0-only
License-File: LICENSE
Classifier: Development Status :: 3 - Alpha
Classifier: Programming Language :: Python :: 3
Classifier: Programming Language :: Python :: 3.9
Classifier: Programming Language :: Python :: 3.10
Classifier: Programming Language :: Python :: 3.11
Classifier: Programming Language :: Python :: 3.12
Classifier: Programming Language :: Python :: 3.13
Classifier: Operating System :: POSIX :: Linux
Classifier: Intended Audience :: Science/Research
Classifier: Topic :: Scientific/Engineering :: Bio-Informatics
Project-URL: documentation, https://x3cflux.readthedocs.io
Project-URL: homepage, https://13cflux.net
Project-URL: repository, https://jugit.fz-juelich.de/IBG-1/ModSim/Fluxomics/13CFLUX
Requires-Python: >=3.9
Requires-Dist: numpy
Requires-Dist: scipy
Requires-Dist: joblib
Requires-Dist: cvxpy
Requires-Dist: cyipopt
Requires-Dist: hopsy>=1.6.1
Provides-Extra: test
Requires-Dist: pytest; extra == "test"
Requires-Dist: pytest-cov; extra == "test"
